.gitignore
MANIFEST.in
README.rst
setup.cfg
setup.py
Products/__init__.py
Products.jsImagePopups.egg-info/PKG-INFO
Products.jsImagePopups.egg-info/SOURCES.txt
Products.jsImagePopups.egg-info/dependency_links.txt
Products.jsImagePopups.egg-info/entry_points.txt
Products.jsImagePopups.egg-info/namespace_packages.txt
Products.jsImagePopups.egg-info/not-zip-safe
Products.jsImagePopups.egg-info/requires.txt
Products.jsImagePopups.egg-info/top_level.txt
Products/jsImagePopups/__init__.py
Products/jsImagePopups/configure.zcml
Products/jsImagePopups/browser/__init__.py
Products/jsImagePopups/browser/blank.gif
Products/jsImagePopups/browser/close.gif
Products/jsImagePopups/browser/configure.zcml
Products/jsImagePopups/browser/lightbox.css
Products/jsImagePopups/browser/lightbox.init.js
Products/jsImagePopups/browser/lightbox.js
Products/jsImagePopups/browser/loading.gif
Products/jsImagePopups/browser/next.gif
Products/jsImagePopups/browser/prev.gif
Products/jsImagePopups/profiles/default/cssregistry.xml
Products/jsImagePopups/profiles/default/jsregistry.xml
Products/jsImagePopups/profiles/default/metadata.xml
Products/jsImagePopups/profiles/default/propertiestool.xml
Products/jsImagePopups/profiles/default/skins.xml
Products/jsImagePopups/skins/jsimagepopups/lightbox.settings.js.py
docs/HISTORY.txt