Metadata-Version: 1.1
Name: Products.jsImagePopups
Version: 2.0b8
Summary: Provides lightbox functionality for images
Home-page: https://github.com/Raptus/Products.jsImagePopups
Author: Raptus AG
Author-email: dev@raptus.com
License: GPL
Platform: UNKNOWN
Classifier: Programming Language :: Python
Classifier: Topic :: Software Development :: Libraries :: Python Modules
